{
    "type": "success",
    "code": 1000,
    "status": 200,
    "message": "Video metadata successfully retrieved",
    "result": {
        "audio_descriptions": [
            {
                "audio_clips": [
                    {
                        "_id": "5d33b5b99d41be1e9b2eb274",
                        "video": "5d33b5b99d41be1e9b2eb276",
                        "audio_description": "5d33b5b99d41be1e9b2eb275",
                        "user": "5d33233a9d41be1e9b2eb1dc",
                        "label": "Milk fever",
                        "playback_type": "extended",
                        "start_time": 3.514602,
                        "end_time": 3.514602,
                        "duration": 7.894784580498866,
                        "file_name": "F85cuRuQjLE_5d33b5b99d41be1e9b2eb274.wav",
                        "file_size_bytes": 1392684,
                        "file_mime_type": "audio/wav",
                        "file_path": "/current/F85cuRuQjLE",
                        "created_at": 20190721004545,
                        "__v": 0,
                        "transcript": [
                            {
                                "_id": "5e557e52760423990095245a",
                                "sentence": " A cow is struggling to get up from the ground. A caption tells us, this cow has milk fever.",
                                "start_time": 0.4,
                                "end_time": 6.15
                            },
                            {
                                "_id": "5e557e527604239900952459",
                                "sentence": " This cow needs calcium.",
                                "start_time": 6.23,
                                "end_time": 7.85
                            }
                        ]
                    },
                    {
                        "_id": "5d33b60651c17b210eab2f09",
                        "video": "5d33b5b99d41be1e9b2eb276",
                        "audio_description": "5d33b5b99d41be1e9b2eb275",
                        "user": "5d33233a9d41be1e9b2eb1dc",
                        "label": "",
                        "playback_type": "extended",
                        "start_time": 21.449119,
                        "end_time": 21.449119,
                        "duration": 6.315827664399093,
                        "file_name": "F85cuRuQjLE_5d33b60651c17b210eab2f09.wav",
                        "file_size_bytes": 1114156,
                        "file_mime_type": "audio/wav",
                        "file_path": "/current/F85cuRuQjLE",
                        "created_at": 20190721004702,
                        "__v": 0,
                        "transcript": [
                            {
                                "_id": "5e557e5076042399009523da",
                                "sentence": " A vehicle enters from the back ground and drives over to the cow while playing its siren.",
                                "start_time": 0.96,
                                "end_time": 6.27
                            }
                        ]
                    },
                    {
                        "_id": "5d33b69d51c17b210eab2f0a",
                        "video": "5d33b5b99d41be1e9b2eb276",
                        "audio_description": "5d33b5b99d41be1e9b2eb275",
                        "user": "5d33233a9d41be1e9b2eb1dc",
                        "label": "Car stops",
                        "playback_type": "extended",
                        "start_time": 47.226514,
                        "end_time": 47.226514,
                        "duration": 5.479909297052155,
                        "file_name": "F85cuRuQjLE_5d33b69d51c17b210eab2f0a.wav",
                        "file_size_bytes": 966700,
                        "file_mime_type": "audio/wav",
                        "file_path": "/current/F85cuRuQjLE",
                        "created_at": 20190721004933,
                        "__v": 0,
                        "transcript": [
                            {
                                "_id": "5e5578707604239900952251",
                                "sentence": " The car stops in front of the cow, and a person's shoe",
                                "start_time": 0.53,
                                "end_time": 3.99
                            },
                            {
                                "_id": "5e5578707604239900952250",
                                "sentence": " is seen out of the door.",
                                "start_time": 3.99,
                                "end_time": 5.44
                            }
                        ]
                    },
                    {
                        "_id": "5d33b6c79d41be1e9b2eb277",
                        "video": "5d33b5b99d41be1e9b2eb276",
                        "audio_description": "5d33b5b99d41be1e9b2eb275",
                        "user": "5d33233a9d41be1e9b2eb1dc",
                        "label": "Farmer appears",
                        "playback_type": "extended",
                        "start_time": 55.120174,
                        "end_time": 55.120174,
                        "duration": 7.523265306122449,
                        "file_name": "F85cuRuQjLE_5d33b6c79d41be1e9b2eb277.wav",
                        "file_size_bytes": 1327148,
                        "file_mime_type": "audio/wav",
                        "file_path": "/current/F85cuRuQjLE",
                        "created_at": 20190721005015,
                        "__v": 0,
                        "transcript": [
                            {
                                "_id": "5e55787176042399009522c3",
                                "sentence": " A farmer gets out of the vehicle with a bottle and some tubing. This startles the cow who start shifting in the mud.",
                                "start_time": 0.48,
                                "end_time": 7.48
                            }
                        ]
                    },
                    {
                        "_id": "5d33b70851c17b210eab2f0b",
                        "video": "5d33b5b99d41be1e9b2eb276",
                        "audio_description": "5d33b5b99d41be1e9b2eb275",
                        "user": "5d33233a9d41be1e9b2eb1dc",
                        "label": "Calcijet is shown",
                        "playback_type": "extended",
                        "start_time": 70.429737,
                        "end_time": 70.429737,
                        "duration": 6.130068027210885,
                        "file_name": "F85cuRuQjLE_5d33b70851c17b210eab2f0b.wav",
                        "file_size_bytes": 1081388,
                        "file_mime_type": "audio/wav",
                        "file_path": "/current/F85cuRuQjLE",
                        "created_at": 20190721005120,
                        "__v": 0,
                        "transcript": [
                            {
                                "_id": "5e557b2d760423990095232e",
                                "sentence": " The bottle that the farmer is holding is shown to the camera, and it is labeled couse a jet.",
                                "start_time": 0.37,
                                "end_time": 5.97
                            }
                        ]
                    },
                    {
                        "_id": "5d33b73f51c17b210eab2f0c",
                        "video": "5d33b5b99d41be1e9b2eb276",
                        "audio_description": "5d33b5b99d41be1e9b2eb275",
                        "user": "5d33233a9d41be1e9b2eb1dc",
                        "label": "Farmer attempts injection",
                        "playback_type": "extended",
                        "start_time": 80.359233,
                        "end_time": 80.359233,
                        "duration": 5.758548752834467,
                        "file_name": "F85cuRuQjLE_5d33b73f51c17b210eab2f0c.wav",
                        "file_size_bytes": 1015852,
                        "file_mime_type": "audio/wav",
                        "file_path": "/current/F85cuRuQjLE",
                        "created_at": 20190721005215,
                        "__v": 0,
                        "transcript": [
                            {
                                "_id": "5e557b2e76042399009523a3",
                                "sentence": " As the farmer approaches, the cow the cow thrashes around in response to him.",
                                "start_time": 0.56,
                                "end_time": 5.48
                            }
                        ]
                    },
                    {
                        "_id": "5d33b7689d41be1e9b2eb278",
                        "video": "5d33b5b99d41be1e9b2eb276",
                        "audio_description": "5d33b5b99d41be1e9b2eb275",
                        "user": "5d33233a9d41be1e9b2eb1dc",
                        "label": "The milk vein ",
                        "playback_type": "extended",
                        "start_time": 85.345328,
                        "end_time": 85.345328,
                        "duration": 6.315827664399093,
                        "file_name": "F85cuRuQjLE_5d33b7689d41be1e9b2eb278.wav",
                        "file_size_bytes": 1114156,
                        "file_mime_type": "audio/wav",
                        "file_path": "/current/F85cuRuQjLE",
                        "created_at": 20190721005256,
                        "__v": 0,
                        "transcript": [
                            {
                                "_id": "5e5579b87f8232990368e842",
                                "sentence": " A caption appears and reads one bottle into milk vein via the flutter valve.",
                                "start_time": 0.22,
                                "end_time": 6.27
                            }
                        ]
                    },
                    {
                        "_id": "5d33b78951c17b210eab2f0d",
                        "video": "5d33b5b99d41be1e9b2eb276",
                        "audio_description": "5d33b5b99d41be1e9b2eb275",
                        "user": "5d33233a9d41be1e9b2eb1dc",
                        "label": "Cow is pricked with needle",
                        "playback_type": "extended",
                        "start_time": 88.134134,
                        "end_time": 88.134134,
                        "duration": 4.272471655328798,
                        "file_name": "F85cuRuQjLE_5d33b78951c17b210eab2f0d.wav",
                        "file_size_bytes": 753708,
                        "file_mime_type": "audio/wav",
                        "file_path": "/current/F85cuRuQjLE",
                        "created_at": 20190721005329,
                        "__v": 0,
                        "transcript": [
                            {
                                "_id": "5e557e5076042399009523cd",
                                "sentence": " The farmer places the tubing into the cow using a needle.",
                                "start_time": 0.34,
                                "end_time": 4.19
                            }
                        ]
                    },
                    {
                        "_id": "5d33b7c99d41be1e9b2eb279",
                        "video": "5d33b5b99d41be1e9b2eb276",
                        "audio_description": "5d33b5b99d41be1e9b2eb275",
                        "user": "5d33233a9d41be1e9b2eb1dc",
                        "label": "Cow\u2019s face in mud",
                        "playback_type": "extended",
                        "start_time": 117.366304,
                        "end_time": 117.366304,
                        "duration": 3.900952380952381,
                        "file_name": "F85cuRuQjLE_5d33b7c99d41be1e9b2eb279.wav",
                        "file_size_bytes": 688172,
                        "file_mime_type": "audio/wav",
                        "file_path": "/current/F85cuRuQjLE",
                        "created_at": 20190721005433,
                        "__v": 0,
                        "transcript": [
                            {
                                "_id": "5e557bad14a7ae98ff6a9a53",
                                "sentence": " The cows face is shown still stuck in the mud.",
                                "start_time": 0.79,
                                "end_time": 3.86
                            }
                        ]
                    },
                    {
                        "_id": "5d33b7f49d41be1e9b2eb27a",
                        "video": "5d33b5b99d41be1e9b2eb276",
                        "audio_description": "5d33b5b99d41be1e9b2eb275",
                        "user": "5d33233a9d41be1e9b2eb1dc",
                        "label": "Caption about mud",
                        "playback_type": "extended",
                        "start_time": 121.339642,
                        "end_time": 121.339642,
                        "duration": 5.479909297052155,
                        "file_name": "F85cuRuQjLE_5d33b7f49d41be1e9b2eb27a.wav",
                        "file_size_bytes": 966700,
                        "file_mime_type": "audio/wav",
                        "file_path": "/current/F85cuRuQjLE",
                        "created_at": 20190721005516,
                        "__v": 0,
                        "transcript": [
                            {
                                "_id": "5e557e51760423990095241d",
                                "sentence": " A caption appears which says fields are getting muddy, heavy rain last night.",
                                "start_time": 0.42,
                                "end_time": 5.44
                            }
                        ]
                    },
                    {
                        "_id": "5d33b8129d41be1e9b2eb27b",
                        "video": "5d33b5b99d41be1e9b2eb276",
                        "audio_description": "5d33b5b99d41be1e9b2eb275",
                        "user": "5d33233a9d41be1e9b2eb1dc",
                        "label": "Rope around cow\u2019s head",
                        "playback_type": "extended",
                        "start_time": 126.411375,
                        "end_time": 126.411375,
                        "duration": 4.73687074829932,
                        "file_name": "F85cuRuQjLE_5d33b8129d41be1e9b2eb27b.wav",
                        "file_size_bytes": 835628,
                        "file_mime_type": "audio/wav",
                        "file_path": "/current/F85cuRuQjLE",
                        "created_at": 20190721005546,
                        "__v": 0,
                        "transcript": [
                            {
                                "_id": "5e557e517604239900952405",
                                "sentence": " A rope has been placed her over the cows mouth and around its head.",
                                "start_time": 0.65,
                                "end_time": 4.69
                            }
                        ]
                    },
                    {
                        "_id": "5d33b83d51c17b210eab2f0e",
                        "video": "5d33b5b99d41be1e9b2eb276",
                        "audio_description": "5d33b5b99d41be1e9b2eb275",
                        "user": "5d33233a9d41be1e9b2eb1dc",
                        "label": "First attempt to lift cow",
                        "playback_type": "extended",
                        "start_time": 139.500147,
                        "end_time": 139.500147,
                        "duration": 6.03718820861678,
                        "file_name": "F85cuRuQjLE_5d33b83d51c17b210eab2f0e.wav",
                        "file_size_bytes": 1065004,
                        "file_mime_type": "audio/wav",
                        "file_path": "/current/F85cuRuQjLE",
                        "created_at": 20190721005629,
                        "__v": 0,
                        "transcript": [
                            {
                                "_id": "5e557e51760423990095244c",
                                "sentence": " The farmer is back in his car and is attempting to pull the cow back onto its feet.",
                                "start_time": 0.26,
                                "end_time": 5.92
                            }
                        ]
                    },
                    {
                        "_id": "5d33b8ba51c17b210eab2f10",
                        "video": "5d33b5b99d41be1e9b2eb276",
                        "audio_description": "5d33b5b99d41be1e9b2eb275",
                        "user": "5d33233a9d41be1e9b2eb1dc",
                        "label": "Second attempt to lift cow",
                        "playback_type": "extended",
                        "start_time": 148.4348051948052,
                        "end_time": 148.4348051948052,
                        "duration": 6.501587301587302,
                        "file_name": "F85cuRuQjLE_5d33b8ba51c17b210eab2f10.wav",
                        "file_size_bytes": 1146924,
                        "file_mime_type": "audio/wav",
                        "file_path": "/current/F85cuRuQjLE",
                        "created_at": 20190721005834,
                        "__v": 0,
                        "transcript": [
                            {
                                "_id": "5e5579b87f8232990368e875",
                                "sentence": " The farmer is unsuccessful and gets back out of his vehicle to try and pull the rope up with his hand.",
                                "start_time": 0.01,
                                "end_time": 6.46
                            }
                        ]
                    },
                    {
                        "_id": "5d33b8e851c17b210eab2f11",
                        "video": "5d33b5b99d41be1e9b2eb276",
                        "audio_description": "5d33b5b99d41be1e9b2eb275",
                        "user": "5d33233a9d41be1e9b2eb1dc",
                        "label": "Cow stands",
                        "playback_type": "extended",
                        "start_time": 165.489882,
                        "end_time": 165.489882,
                        "duration": 3.5294331065759637,
                        "file_name": "F85cuRuQjLE_5d33b8e851c17b210eab2f11.wav",
                        "file_size_bytes": 622636,
                        "file_mime_type": "audio/wav",
                        "file_path": "/current/F85cuRuQjLE",
                        "created_at": 20190721005920,
                        "__v": 0,
                        "transcript": [
                            {
                                "_id": "5e557b2e7604239900952391",
                                "sentence": " The farmer removes the rope, and the cow stands up.",
                                "start_time": 0.29,
                                "end_time": 3.46
                            }
                        ]
                    },
                    {
                        "_id": "5d33b90851c17b210eab2f12",
                        "video": "5d33b5b99d41be1e9b2eb276",
                        "audio_description": "5d33b5b99d41be1e9b2eb275",
                        "user": "5d33233a9d41be1e9b2eb1dc",
                        "label": "Cow continues to stand",
                        "playback_type": "extended",
                        "start_time": 170.330114,
                        "end_time": 170.330114,
                        "duration": 7.151746031746032,
                        "file_name": "F85cuRuQjLE_5d33b90851c17b210eab2f12.wav",
                        "file_size_bytes": 1261612,
                        "file_mime_type": "audio/wav",
                        "file_path": "/current/F85cuRuQjLE",
                        "created_at": 20190721005952,
                        "__v": 0,
                        "transcript": [
                            {
                                "_id": "5e5579b97f8232990368e884",
                                "sentence": " The cow is standing up, and a caption reads, five minutes later, she is on her feet, looking a bit dazed.",
                                "start_time": 0.46,
                                "end_time": 7.02
                            }
                        ]
                    },
                    {
                        "_id": "5d33b94851c17b210eab2f13",
                        "video": "5d33b5b99d41be1e9b2eb276",
                        "audio_description": "5d33b5b99d41be1e9b2eb275",
                        "user": "5d33233a9d41be1e9b2eb1dc",
                        "label": "Off to find her calf",
                        "playback_type": "extended",
                        "start_time": 191.384091,
                        "end_time": 191.384091,
                        "duration": 5.201269841269841,
                        "file_name": "F85cuRuQjLE_5d33b94851c17b210eab2f13.wav",
                        "file_size_bytes": 917548,
                        "file_mime_type": "audio/wav",
                        "file_path": "/current/F85cuRuQjLE",
                        "created_at": 20190721010056,
                        "__v": 0,
                        "transcript": [
                            {
                                "_id": "5e557b2e7604239900952385",
                                "sentence": " The cow begins to walk away. As a caption reads off to find her calf.",
                                "start_time": 0.22,
                                "end_time": 5.13
                            }
                        ]
                    }
                ],
                "_id": "5d33b5b99d41be1e9b2eb275",
                "video": "5d33b5b99d41be1e9b2eb276",
                "user": {
                    "opt_in": [],
                    "_id": "5d33233a9d41be1e9b2eb1dc",
                    "email": "sdebellis2@fordham.edu",
                    "name": "Steven DeBellis",
                    "given_name": "Steven",
                    "picture": "https://lh6.googleusercontent.com/-MCME78vIm5M/AAAAAAAAAAI/AAAAAAAAACw/6LM4wCl7CWI/s96-c/photo.jpg",
                    "locale": "en",
                    "google_user_id": "117772413204611873219",
                    "last_login": 20190721004323,
                    "token": "c06d9cfc30d4659be7e2353b0eb8d0370c3f9a81b05a15c504151a2cd4fbd31e",
                    "__v": 0,
                    "updated_at": 20190721004323,
                    "policy_review": ""
                },
                "status": "published",
                "language": "en-us",
                "created_at": 20190721004545,
                "updated_at": 20190721004545,
                "notes": "",
                "__v": 0,
                "admin_review": "",
                "feedbacks": {}
            }
        ],
        "tags": [
            "holstein",
            "cows",
            "dairy",
            "farm",
            "texas",
            "drought",
            "horse",
            "pony",
            "irene",
            "vet"
        ],
        "custom_tags": [],
        "_id": "5d33b5b99d41be1e9b2eb276",
        "title": "Cow goes down with milk fever",
        "description": "She calved yesterday. Found her this morning lying flat out but 1 bottle of calcium and she was back on her feet after just 5 mins. First thing she done after getting up was top search for her Swedish red x Holstein calf",
        "youtube_id": "F85cuRuQjLE",
        "created_at": 20190721004545,
        "updated_at": 20190721010057,
        "views": 0,
        "__v": 0,
        "youtube_status": "available",
        "category": "Pets & Animals",
        "category_id": "15",
        "duration": 194
    }
}